Metadata-Version: 2.1
Name: walkway
Version: 0.0.8
Summary: Motion detector for a narrow runway
Home-page: https://github.com/leomol/walkway
Author: Leo Molina
Author-email: leonardomt@gmail.com
License: UNKNOWN
Project-URL: Bug Tracker, https://github.com/leomol/walkway/issues
Keywords: walkway,sidewalk,runway,gait,locomotion,motion,movement,tracker,catwalk,FLIR,SpinView,Spinnaker,BlackFly,mouse,rat
Platform: UNKNOWN
Classifier: Operating System :: OS Independent
Classifier: Development Status :: 3 - Alpha
Classifier: Intended Audience :: Science/Research
Classifier: Topic :: Scientific/Engineering :: Image Processing
Classifier: License :: OSI Approved :: GNU General Public License v3 (GPLv3)
Classifier: Programming Language :: Python :: 3.8
Requires-Python: >=3.8
License-File: LICENSE.md
